[{"InstanceId":"1210546933b7479a86553bf8560b4af0","Name":"Jab 1","OwnerId":31,"Owner":"Mewtwo","HitboxActive":"6","FirstActionableFrame":"25","BaseDamage":"4","Angle":"76/70","BaseKnockBackSetKnockback":"50/20","LandingLag":null,"AutoCancel":null,"KnockbackGrowth":"20/60","MoveType":"ground","IsWeightDependent":false,"Game":"Smash4","Related":{"Smash4":{"Character":"http://api.kuroganehammer.com/api/characters/name/Mewtwo?game=smash4","Self":"http://api.kuroganehammer.com/api/moves/1210546933b7479a86553bf8560b4af0?game=smash4"},"Ultimate":{"Character":"http://api.kuroganehammer.com/api/characters/name/Mewtwo?game=ultimate"}},"Links":[{"Rel":"self","Href":"http://api.kuroganehammer.com/api/moves/1210546933b7479a86553bf8560b4af0?game=smash4"},{"Rel":"character","Href":"http://api.kuroganehammer.com/api/characters/name/Mewtwo?game=smash4"}]},{"InstanceId":"8f22219572f44b9eaa7404c2e2c6cfb4","Name":"Rapid Jab Finisher","OwnerId":31,"Owner":"Mewtwo","HitboxActive":"6","FirstActionableFrame":"36","BaseDamage":"2","Angle":"361","BaseKnockBackSetKnockback":"82","LandingLag":null,"AutoCancel":null,"KnockbackGrowth":"100","MoveType":"ground","IsWeightDependent":false,"Game":"Smash4","Related":{"Smash4":{"Character":"http://api.kuroganehammer.com/api/characters/name/Mewtwo?game=smash4","Self":"http://api.kuroganehammer.com/api/moves/8f22219572f44b9eaa7404c2e2c6cfb4?game=smash4"},"Ultimate":{"Character":"http://api.kuroganehammer.com/api/characters/name/Mewtwo?game=ultimate"}},"Links":[{"Rel":"self","Href":"http://api.kuroganehammer.com/api/moves/8f22219572f44b9eaa7404c2e2c6cfb4?game=smash4"},{"Rel":"character","Href":"http://api.kuroganehammer.com/api/characters/name/Mewtwo?game=smash4"}]},{"InstanceId":"816ab769ef3e4f3ea0e0950a6e17694f","Name":"Dash Attack","OwnerId":31,"Owner":"Mewtwo","HitboxActive":"10-11","FirstActionableFrame":"39","BaseDamage":"10/9","Angle":"60/70","BaseKnockBackSetKnockback":"80","LandingLag":null,"AutoCancel":null,"KnockbackGrowth":"70/60","MoveType":"ground","IsWeightDependent":false,"Game":"Smash4","Related":{"Smash4":{"Character":"http://api.kuroganehammer.com/api/characters/name/Mewtwo?game=smash4","Self":"http://api.kuroganehammer.com/api/moves/816ab769ef3e4f3ea0e0950a6e17694f?game=smash4"},"Ultimate":{"Character":"http://api.kuroganehammer.com/api/characters/name/Mewtwo?game=ultimate"}},"Links":[{"Rel":"self","Href":"http://api.kuroganehammer.com/api/moves/816ab769ef3e4f3ea0e0950a6e17694f?game=smash4"},{"Rel":"character","Href":"http://api.kuroganehammer.com/api/characters/name/Mewtwo?game=smash4"}]},{"InstanceId":"9303a54c6cec4fb7ba74b4eaa1b1ba87","Name":"Dash Attack (Late)","OwnerId":31,"Owner":"Mewtwo","HitboxActive":"12-20","FirstActionableFrame":"-","BaseDamage":"6/4","Angle":"70/80","BaseKnockBackSetKnockback":"80","LandingLag":null,"AutoCancel":null,"KnockbackGrowth":"70/60","MoveType":"ground","IsWeightDependent":false,"Game":"Smash4","Related":{"Smash4":{"Character":"http://api.kuroganehammer.com/api/characters/name/Mewtwo?game=smash4","Self":"http://api.kuroganehammer.com/api/moves/9303a54c6cec4fb7ba74b4eaa1b1ba87?game=smash4"},"Ultimate":{"Character":"http://api.kuroganehammer.com/api/characters/name/Mewtwo?game=ultimate"}},"Links":[{"Rel":"self","Href":"http://api.kuroganehammer.com/api/moves/9303a54c6cec4fb7ba74b4eaa1b1ba87?game=smash4"},{"Rel":"character","Href":"http://api.kuroganehammer.com/api/characters/name/Mewtwo?game=smash4"}]},{"InstanceId":"c319547339434b11a59eeda46398f3ef","Name":"Ftilt (All Angles)","OwnerId":31,"Owner":"Mewtwo","HitboxActive":"10-11","FirstActionableFrame":"36","BaseDamage":"10/9/8","Angle":"361","BaseKnockBackSetKnockback":"20","LandingLag":null,"AutoCancel":null,"KnockbackGrowth":"100","MoveType":"ground","IsWeightDependent":false,"Game":"Smash4","Related":{"Smash4":{"Character":"http://api.kuroganehammer.com/api/characters/name/Mewtwo?game=smash4","Self":"http://api.kuroganehammer.com/api/moves/c319547339434b11a59eeda46398f3ef?game=smash4"},"Ultimate":{"Character":"http://api.kuroganehammer.com/api/characters/name/Mewtwo?game=ultimate"}},"Links":[{"Rel":"self","Href":"http://api.kuroganehammer.com/api/moves/c319547339434b11a59eeda46398f3ef?game=smash4"},{"Rel":"character","Href":"http://api.kuroganehammer.com/api/characters/name/Mewtwo?game=smash4"}]},{"InstanceId":"33a216f1c8364c8688a75291aad01e51","Name":"Utilt","OwnerId":31,"Owner":"Mewtwo","HitboxActive":"8","FirstActionableFrame":"30","BaseDamage":"6/5/4.5/4.5","Angle":"110/110/361/110","BaseKnockBackSetKnockback":"70/60/50/50","LandingLag":null,"AutoCancel":null,"KnockbackGrowth":"114/114/80/50","MoveType":"ground","IsWeightDependent":false,"Game":"Smash4","Related":{"Smash4":{"Character":"http://api.kuroganehammer.com/api/characters/name/Mewtwo?game=smash4","Self":"http://api.kuroganehammer.com/api/moves/33a216f1c8364c8688a75291aad01e51?game=smash4"},"Ultimate":{"Character":"http://api.kuroganehammer.com/api/characters/name/Mewtwo?game=ultimate"}},"Links":[{"Rel":"self","Href":"http://api.kuroganehammer.com/api/moves/33a216f1c8364c8688a75291aad01e51?game=smash4"},{"Rel":"character","Href":"http://api.kuroganehammer.com/api/characters/name/Mewtwo?game=smash4"}]},{"InstanceId":"2c338e73eccd447fbbed29d1406b8858","Name":"Utilt (Late)","OwnerId":31,"Owner":"Mewtwo","HitboxActive":"9-13","FirstActionableFrame":"-","BaseDamage":"5/4/3","Angle":"78","BaseKnockBackSetKnockback":"60/50/40","LandingLag":null,"AutoCancel":null,"KnockbackGrowth":"114","MoveType":"ground","IsWeightDependent":false,"Game":"Smash4","Related":{"Smash4":{"Character":"http://api.kuroganehammer.com/api/characters/name/Mewtwo?game=smash4","Self":"http://api.kuroganehammer.com/api/moves/2c338e73eccd447fbbed29d1406b8858?game=smash4"},"Ultimate":{"Character":"http://api.kuroganehammer.com/api/characters/name/Mewtwo?game=ultimate"}},"Links":[{"Rel":"self","Href":"http://api.kuroganehammer.com/api/moves/2c338e73eccd447fbbed29d1406b8858?game=smash4"},{"Rel":"character","Href":"http://api.kuroganehammer.com/api/characters/name/Mewtwo?game=smash4"}]},{"InstanceId":"f541d980eb3741a4b978cd56ac75b88e","Name":"Dtilt","OwnerId":31,"Owner":"Mewtwo","HitboxActive":"6-7","FirstActionableFrame":"21","BaseDamage":"5/4.5/4","Angle":"80/70/60","BaseKnockBackSetKnockback":"60/65/60","LandingLag":null,"AutoCancel":null,"KnockbackGrowth":"82/84/70","MoveType":"ground","IsWeightDependent":false,"Game":"Smash4","Related":{"Smash4":{"Character":"http://api.kuroganehammer.com/api/characters/name/Mewtwo?game=smash4","Self":"http://api.kuroganehammer.com/api/moves/f541d980eb3741a4b978cd56ac75b88e?game=smash4"},"Ultimate":{"Character":"http://api.kuroganehammer.com/api/characters/name/Mewtwo?game=ultimate"}},"Links":[{"Rel":"self","Href":"http://api.kuroganehammer.com/api/moves/f541d980eb3741a4b978cd56ac75b88e?game=smash4"},{"Rel":"character","Href":"http://api.kuroganehammer.com/api/characters/name/Mewtwo?game=smash4"}]},{"InstanceId":"71fb58bd6c44416b88264faa5d2ba542","Name":"Fsmash","OwnerId":31,"Owner":"Mewtwo","HitboxActive":"19-21","FirstActionableFrame":"53","BaseDamage":"16/19","Angle":"361","BaseKnockBackSetKnockback":"30/21","LandingLag":null,"AutoCancel":null,"KnockbackGrowth":"90/85","MoveType":"ground","IsWeightDependent":false,"Game":"Smash4","Related":{"Smash4":{"Character":"http://api.kuroganehammer.com/api/characters/name/Mewtwo?game=smash4","Self":"http://api.kuroganehammer.com/api/moves/71fb58bd6c44416b88264faa5d2ba542?game=smash4"},"Ultimate":{"Character":"http://api.kuroganehammer.com/api/characters/name/Mewtwo?game=ultimate"}},"Links":[{"Rel":"self","Href":"http://api.kuroganehammer.com/api/moves/71fb58bd6c44416b88264faa5d2ba542?game=smash4"},{"Rel":"character","Href":"http://api.kuroganehammer.com/api/characters/name/Mewtwo?game=smash4"}]},{"InstanceId":"d97b9ec55f65460f8b0aa2d8bdda1917","Name":"Usmash (Hit 1)","OwnerId":31,"Owner":"Mewtwo","HitboxActive":"9","FirstActionableFrame":"69","BaseDamage":"1","Angle":"100","BaseKnockBackSetKnockback":"W: 90","LandingLag":null,"AutoCancel":null,"KnockbackGrowth":"100","MoveType":"ground","IsWeightDependent":false,"Game":"Smash4","Related":{"Smash4":{"Character":"http://api.kuroganehammer.com/api/characters/name/Mewtwo?game=smash4","Self":"http://api.kuroganehammer.com/api/moves/d97b9ec55f65460f8b0aa2d8bdda1917?game=smash4"},"Ultimate":{"Character":"http://api.kuroganehammer.com/api/characters/name/Mewtwo?game=ultimate"}},"Links":[{"Rel":"self","Href":"http://api.kuroganehammer.com/api/moves/d97b9ec55f65460f8b0aa2d8bdda1917?game=smash4"},{"Rel":"character","Href":"http://api.kuroganehammer.com/api/characters/name/Mewtwo?game=smash4"}]},{"InstanceId":"f4417de3c78d4d34b4aa45cdb55113e7","Name":"Usmash (Hit 1, Late)","OwnerId":31,"Owner":"Mewtwo","HitboxActive":"10-11","FirstActionableFrame":"-","BaseDamage":"1","Angle":"170/170/95/270","BaseKnockBackSetKnockback":"W: 18/18/40/5","LandingLag":null,"AutoCancel":null,"KnockbackGrowth":"100","MoveType":"ground","IsWeightDependent":false,"Game":"Smash4","Related":{"Smash4":{"Character":"http://api.kuroganehammer.com/api/characters/name/Mewtwo?game=smash4","Self":"http://api.kuroganehammer.com/api/moves/f4417de3c78d4d34b4aa45cdb55113e7?game=smash4"},"Ultimate":{"Character":"http://api.kuroganehammer.com/api/characters/name/Mewtwo?game=ultimate"}},"Links":[{"Rel":"self","Href":"http://api.kuroganehammer.com/api/moves/f4417de3c78d4d34b4aa45cdb55113e7?game=smash4"},{"Rel":"character","Href":"http://api.kuroganehammer.com/api/characters/name/Mewtwo?game=smash4"}]},{"InstanceId":"2aff23ab06e246c29ca8f41bf7a19a3f","Name":"Usmash (Hits 2-6)","OwnerId":31,"Owner":"Mewtwo","HitboxActive":"14-15, 18-19, 22-23, 26-27, 30-31","FirstActionableFrame":"-","BaseDamage":"1","Angle":"170/170/95/270","BaseKnockBackSetKnockback":"W: 18/18/40/5","LandingLag":null,"AutoCancel":null,"KnockbackGrowth":"100","MoveType":"ground","IsWeightDependent":false,"Game":"Smash4","Related":{"Smash4":{"Character":"http://api.kuroganehammer.com/api/characters/name/Mewtwo?game=smash4","Self":"http://api.kuroganehammer.com/api/moves/2aff23ab06e246c29ca8f41bf7a19a3f?game=smash4"},"Ultimate":{"Character":"http://api.kuroganehammer.com/api/characters/name/Mewtwo?game=ultimate"}},"Links":[{"Rel":"self","Href":"http://api.kuroganehammer.com/api/moves/2aff23ab06e246c29ca8f41bf7a19a3f?game=smash4"},{"Rel":"character","Href":"http://api.kuroganehammer.com/api/characters/name/Mewtwo?game=smash4"}]},{"InstanceId":"1c0d0bb874ac4045852d5bf456256023","Name":"Usmash (Hit 7)","OwnerId":31,"Owner":"Mewtwo","HitboxActive":"34-35","FirstActionableFrame":"-","BaseDamage":"10","Angle":"80/80/90/90","BaseKnockBackSetKnockback":"60","LandingLag":null,"AutoCancel":null,"KnockbackGrowth":"107","MoveType":"ground","IsWeightDependent":false,"Game":"Smash4","Related":{"Smash4":{"Character":"http://api.kuroganehammer.com/api/characters/name/Mewtwo?game=smash4","Self":"http://api.kuroganehammer.com/api/moves/1c0d0bb874ac4045852d5bf456256023?game=smash4"},"Ultimate":{"Character":"http://api.kuroganehammer.com/api/characters/name/Mewtwo?game=ultimate"}},"Links":[{"Rel":"self","Href":"http://api.kuroganehammer.com/api/moves/1c0d0bb874ac4045852d5bf456256023?game=smash4"},{"Rel":"character","Href":"http://api.kuroganehammer.com/api/characters/name/Mewtwo?game=smash4"}]},{"InstanceId":"6f382df46a5f4d3db9f939cce77f6407","Name":"Dsmash","OwnerId":31,"Owner":"Mewtwo","HitboxActive":"21-22","FirstActionableFrame":"44","BaseDamage":"15","Angle":"55","BaseKnockBackSetKnockback":"20","LandingLag":null,"AutoCancel":null,"KnockbackGrowth":"118","MoveType":"ground","IsWeightDependent":false,"Game":"Smash4","Related":{"Smash4":{"Character":"http://api.kuroganehammer.com/api/characters/name/Mewtwo?game=smash4","Self":"http://api.kuroganehammer.com/api/moves/6f382df46a5f4d3db9f939cce77f6407?game=smash4"},"Ultimate":{"Character":"http://api.kuroganehammer.com/api/characters/name/Mewtwo?game=ultimate"}},"Links":[{"Rel":"self","Href":"http://api.kuroganehammer.com/api/moves/6f382df46a5f4d3db9f939cce77f6407?game=smash4"},{"Rel":"character","Href":"http://api.kuroganehammer.com/api/characters/name/Mewtwo?game=smash4"}]},{"InstanceId":"fe1612f0a3774aa1b0a467aa5cb08053","Name":"Standing Grab","OwnerId":31,"Owner":"Mewtwo","HitboxActive":"7-8","FirstActionableFrame":"36","BaseDamage":"","Angle":"","BaseKnockBackSetKnockback":"","LandingLag":null,"AutoCancel":null,"KnockbackGrowth":"","MoveType":"ground","IsWeightDependent":false,"Game":"Smash4","Related":{"Smash4":{"Character":"http://api.kuroganehammer.com/api/characters/name/Mewtwo?game=smash4","Self":"http://api.kuroganehammer.com/api/moves/fe1612f0a3774aa1b0a467aa5cb08053?game=smash4"},"Ultimate":{"Character":"http://api.kuroganehammer.com/api/characters/name/Mewtwo?game=ultimate"}},"Links":[{"Rel":"self","Href":"http://api.kuroganehammer.com/api/moves/fe1612f0a3774aa1b0a467aa5cb08053?game=smash4"},{"Rel":"character","Href":"http://api.kuroganehammer.com/api/characters/name/Mewtwo?game=smash4"}]},{"InstanceId":"4f61b48f3d2e4fcf8961e857910cc3cf","Name":"Dash Grab","OwnerId":31,"Owner":"Mewtwo","HitboxActive":"9-10","FirstActionableFrame":"43","BaseDamage":"","Angle":"","BaseKnockBackSetKnockback":"","LandingLag":null,"AutoCancel":null,"KnockbackGrowth":"","MoveType":"ground","IsWeightDependent":false,"Game":"Smash4","Related":{"Smash4":{"Character":"http://api.kuroganehammer.com/api/characters/name/Mewtwo?game=smash4","Self":"http://api.kuroganehammer.com/api/moves/4f61b48f3d2e4fcf8961e857910cc3cf?game=smash4"},"Ultimate":{"Character":"http://api.kuroganehammer.com/api/characters/name/Mewtwo?game=ultimate"}},"Links":[{"Rel":"self","Href":"http://api.kuroganehammer.com/api/moves/4f61b48f3d2e4fcf8961e857910cc3cf?game=smash4"},{"Rel":"character","Href":"http://api.kuroganehammer.com/api/characters/name/Mewtwo?game=smash4"}]},{"InstanceId":"d42f793acc4c4a11b32e4d6f30621b64","Name":"Pivot Grab","OwnerId":31,"Owner":"Mewtwo","HitboxActive":"10-11","FirstActionableFrame":"41","BaseDamage":"","Angle":"","BaseKnockBackSetKnockback":"","LandingLag":null,"AutoCancel":null,"KnockbackGrowth":"","MoveType":"ground","IsWeightDependent":false,"Game":"Smash4","Related":{"Smash4":{"Character":"http://api.kuroganehammer.com/api/characters/name/Mewtwo?game=smash4","Self":"http://api.kuroganehammer.com/api/moves/d42f793acc4c4a11b32e4d6f30621b64?game=smash4"},"Ultimate":{"Character":"http://api.kuroganehammer.com/api/characters/name/Mewtwo?game=ultimate"}},"Links":[{"Rel":"self","Href":"http://api.kuroganehammer.com/api/moves/d42f793acc4c4a11b32e4d6f30621b64?game=smash4"},{"Rel":"character","Href":"http://api.kuroganehammer.com/api/characters/name/Mewtwo?game=smash4"}]},{"InstanceId":"9fdf40e3b75841e2a29a4c47a00444a2","Name":"Spotdodge","OwnerId":31,"Owner":"Mewtwo","HitboxActive":"2-14","FirstActionableFrame":"25","BaseDamage":"","Angle":"","BaseKnockBackSetKnockback":"","LandingLag":null,"AutoCancel":null,"KnockbackGrowth":"","MoveType":"ground","IsWeightDependent":false,"Game":"Smash4","Related":{"Smash4":{"Character":"http://api.kuroganehammer.com/api/characters/name/Mewtwo?game=smash4","Self":"http://api.kuroganehammer.com/api/moves/9fdf40e3b75841e2a29a4c47a00444a2?game=smash4"},"Ultimate":{"Character":"http://api.kuroganehammer.com/api/characters/name/Mewtwo?game=ultimate"}},"Links":[{"Rel":"self","Href":"http://api.kuroganehammer.com/api/moves/9fdf40e3b75841e2a29a4c47a00444a2?game=smash4"},{"Rel":"character","Href":"http://api.kuroganehammer.com/api/characters/name/Mewtwo?game=smash4"}]},{"InstanceId":"4f53295506a046a693e32c1a6c050f8b","Name":"Forward Roll","OwnerId":31,"Owner":"Mewtwo","HitboxActive":"4-13","FirstActionableFrame":"30","BaseDamage":"","Angle":"","BaseKnockBackSetKnockback":"","LandingLag":null,"AutoCancel":null,"KnockbackGrowth":"","MoveType":"ground","IsWeightDependent":false,"Game":"Smash4","Related":{"Smash4":{"Character":"http://api.kuroganehammer.com/api/characters/name/Mewtwo?game=smash4","Self":"http://api.kuroganehammer.com/api/moves/4f53295506a046a693e32c1a6c050f8b?game=smash4"},"Ultimate":{"Character":"http://api.kuroganehammer.com/api/characters/name/Mewtwo?game=ultimate"}},"Links":[{"Rel":"self","Href":"http://api.kuroganehammer.com/api/moves/4f53295506a046a693e32c1a6c050f8b?game=smash4"},{"Rel":"character","Href":"http://api.kuroganehammer.com/api/characters/name/Mewtwo?game=smash4"}]},{"InstanceId":"215c1952a7ab41aaa247edece1b102aa","Name":"Back Roll","OwnerId":31,"Owner":"Mewtwo","HitboxActive":"4-13","FirstActionableFrame":"30","BaseDamage":"","Angle":"","BaseKnockBackSetKnockback":"","LandingLag":null,"AutoCancel":null,"KnockbackGrowth":"","MoveType":"ground","IsWeightDependent":false,"Game":"Smash4","Related":{"Smash4":{"Character":"http://api.kuroganehammer.com/api/characters/name/Mewtwo?game=smash4","Self":"http://api.kuroganehammer.com/api/moves/215c1952a7ab41aaa247edece1b102aa?game=smash4"},"Ultimate":{"Character":"http://api.kuroganehammer.com/api/characters/name/Mewtwo?game=ultimate"}},"Links":[{"Rel":"self","Href":"http://api.kuroganehammer.com/api/moves/215c1952a7ab41aaa247edece1b102aa?game=smash4"},{"Rel":"character","Href":"http://api.kuroganehammer.com/api/characters/name/Mewtwo?game=smash4"}]},{"InstanceId":"4b87e65bb9c049cfa71c0eeb88a15f4e","Name":"Airdodge","OwnerId":31,"Owner":"Mewtwo","HitboxActive":"2-24","FirstActionableFrame":"29","BaseDamage":"","Angle":"","BaseKnockBackSetKnockback":"","LandingLag":null,"AutoCancel":null,"KnockbackGrowth":"","MoveType":"ground","IsWeightDependent":false,"Game":"Smash4","Related":{"Smash4":{"Character":"http://api.kuroganehammer.com/api/characters/name/Mewtwo?game=smash4","Self":"http://api.kuroganehammer.com/api/moves/4b87e65bb9c049cfa71c0eeb88a15f4e?game=smash4"},"Ultimate":{"Character":"http://api.kuroganehammer.com/api/characters/name/Mewtwo?game=ultimate"}},"Links":[{"Rel":"self","Href":"http://api.kuroganehammer.com/api/moves/4b87e65bb9c049cfa71c0eeb88a15f4e?game=smash4"},{"Rel":"character","Href":"http://api.kuroganehammer.com/api/characters/name/Mewtwo?game=smash4"}]},{"InstanceId":"10cbe90c9a4d470c8788485ebb05db06","Name":"Nair (Hits 1-4)","OwnerId":31,"Owner":"Mewtwo","HitboxActive":"7-8, 11-12, 15-16, 19-20","FirstActionableFrame":"46","BaseDamage":"1","Angle":"185/185/110/110","BaseKnockBackSetKnockback":"W: 22/22/46/46 B: 20","LandingLag":"13","AutoCancel":"46>","KnockbackGrowth":"100","MoveType":"aerial","IsWeightDependent":false,"Game":"Smash4","Related":{"Smash4":{"Character":"http://api.kuroganehammer.com/api/characters/name/Mewtwo?game=smash4","Self":"http://api.kuroganehammer.com/api/moves/10cbe90c9a4d470c8788485ebb05db06?game=smash4"},"Ultimate":{"Character":"http://api.kuroganehammer.com/api/characters/name/Mewtwo?game=ultimate"}},"Links":[{"Rel":"self","Href":"http://api.kuroganehammer.com/api/moves/10cbe90c9a4d470c8788485ebb05db06?game=smash4"},{"Rel":"character","Href":"http://api.kuroganehammer.com/api/characters/name/Mewtwo?game=smash4"}]},{"InstanceId":"1839ac1dbc844605be77ac632ee9ad92","Name":"Nair (Hits 5-8)","OwnerId":31,"Owner":"Mewtwo","HitboxActive":"23-24, 27-28, 31-32, 35-36","FirstActionableFrame":"-","BaseDamage":"1","Angle":"185/185/110/110","BaseKnockBackSetKnockback":"W: 22/22/46/46 B: 20","LandingLag":"-","AutoCancel":"-","KnockbackGrowth":"100","MoveType":"aerial","IsWeightDependent":false,"Game":"Smash4","Related":{"Smash4":{"Character":"http://api.kuroganehammer.com/api/characters/name/Mewtwo?game=smash4","Self":"http://api.kuroganehammer.com/api/moves/1839ac1dbc844605be77ac632ee9ad92?game=smash4"},"Ultimate":{"Character":"http://api.kuroganehammer.com/api/characters/name/Mewtwo?game=ultimate"}},"Links":[{"Rel":"self","Href":"http://api.kuroganehammer.com/api/moves/1839ac1dbc844605be77ac632ee9ad92?game=smash4"},{"Rel":"character","Href":"http://api.kuroganehammer.com/api/characters/name/Mewtwo?game=smash4"}]},{"InstanceId":"631c620c386d427b864f9d073d8297e8","Name":"Nair (Hit 9)","OwnerId":31,"Owner":"Mewtwo","HitboxActive":"39-40","FirstActionableFrame":"-","BaseDamage":"4","Angle":"361","BaseKnockBackSetKnockback":"40","LandingLag":"-","AutoCancel":"-","KnockbackGrowth":"110","MoveType":"aerial","IsWeightDependent":false,"Game":"Smash4","Related":{"Smash4":{"Character":"http://api.kuroganehammer.com/api/characters/name/Mewtwo?game=smash4","Self":"http://api.kuroganehammer.com/api/moves/631c620c386d427b864f9d073d8297e8?game=smash4"},"Ultimate":{"Character":"http://api.kuroganehammer.com/api/characters/name/Mewtwo?game=ultimate"}},"Links":[{"Rel":"self","Href":"http://api.kuroganehammer.com/api/moves/631c620c386d427b864f9d073d8297e8?game=smash4"},{"Rel":"character","Href":"http://api.kuroganehammer.com/api/characters/name/Mewtwo?game=smash4"}]},{"InstanceId":"262082756d464dd3994bbc8ac06e469f","Name":"Fair","OwnerId":31,"Owner":"Mewtwo","HitboxActive":"6-8","FirstActionableFrame":"38","BaseDamage":"13","Angle":"50","BaseKnockBackSetKnockback":"40","LandingLag":"14","AutoCancel":"36>","KnockbackGrowth":"100","MoveType":"aerial","IsWeightDependent":false,"Game":"Smash4","Related":{"Smash4":{"Character":"http://api.kuroganehammer.com/api/characters/name/Mewtwo?game=smash4","Self":"http://api.kuroganehammer.com/api/moves/262082756d464dd3994bbc8ac06e469f?game=smash4"},"Ultimate":{"Character":"http://api.kuroganehammer.com/api/characters/name/Mewtwo?game=ultimate"}},"Links":[{"Rel":"self","Href":"http://api.kuroganehammer.com/api/moves/262082756d464dd3994bbc8ac06e469f?game=smash4"},{"Rel":"character","Href":"http://api.kuroganehammer.com/api/characters/name/Mewtwo?game=smash4"}]},{"InstanceId":"efb9b2c6a02b4b859db5193621a46aeb","Name":"Bair","OwnerId":31,"Owner":"Mewtwo","HitboxActive":"13-17","FirstActionableFrame":"40","BaseDamage":"13/11/9","Angle":"361","BaseKnockBackSetKnockback":"20","LandingLag":"17","AutoCancel":"1-2, 38>","KnockbackGrowth":"90","MoveType":"aerial","IsWeightDependent":false,"Game":"Smash4","Related":{"Smash4":{"Character":"http://api.kuroganehammer.com/api/characters/name/Mewtwo?game=smash4","Self":"http://api.kuroganehammer.com/api/moves/efb9b2c6a02b4b859db5193621a46aeb?game=smash4"},"Ultimate":{"Character":"http://api.kuroganehammer.com/api/characters/name/Mewtwo?game=ultimate"}},"Links":[{"Rel":"self","Href":"http://api.kuroganehammer.com/api/moves/efb9b2c6a02b4b859db5193621a46aeb?game=smash4"},{"Rel":"character","Href":"http://api.kuroganehammer.com/api/characters/name/Mewtwo?game=smash4"}]},{"InstanceId":"f031cd6e200a43c4a864679786e98306","Name":"Uair","OwnerId":31,"Owner":"Mewtwo","HitboxActive":"10-14","FirstActionableFrame":"40","BaseDamage":"11/10/9","Angle":"72/65/55","BaseKnockBackSetKnockback":"40","LandingLag":"13","AutoCancel":"1-2, 36>","KnockbackGrowth":"97","MoveType":"aerial","IsWeightDependent":false,"Game":"Smash4","Related":{"Smash4":{"Character":"http://api.kuroganehammer.com/api/characters/name/Mewtwo?game=smash4","Self":"http://api.kuroganehammer.com/api/moves/f031cd6e200a43c4a864679786e98306?game=smash4"},"Ultimate":{"Character":"http://api.kuroganehammer.com/api/characters/name/Mewtwo?game=ultimate"}},"Links":[{"Rel":"self","Href":"http://api.kuroganehammer.com/api/moves/f031cd6e200a43c4a864679786e98306?game=smash4"},{"Rel":"character","Href":"http://api.kuroganehammer.com/api/characters/name/Mewtwo?game=smash4"}]},{"InstanceId":"3034da2e0ddc49cd882870ee081a3359","Name":"Dair","OwnerId":31,"Owner":"Mewtwo","HitboxActive":"15-18","FirstActionableFrame":"46","BaseDamage":"15/14","Angle":"270/70","BaseKnockBackSetKnockback":"10/20","LandingLag":"18","AutoCancel":"1-3, 42>","KnockbackGrowth":"100/98","MoveType":"aerial","IsWeightDependent":false,"Game":"Smash4","Related":{"Smash4":{"Character":"http://api.kuroganehammer.com/api/characters/name/Mewtwo?game=smash4","Self":"http://api.kuroganehammer.com/api/moves/3034da2e0ddc49cd882870ee081a3359?game=smash4"},"Ultimate":{"Character":"http://api.kuroganehammer.com/api/characters/name/Mewtwo?game=ultimate"}},"Links":[{"Rel":"self","Href":"http://api.kuroganehammer.com/api/moves/3034da2e0ddc49cd882870ee081a3359?game=smash4"},{"Rel":"character","Href":"http://api.kuroganehammer.com/api/characters/name/Mewtwo?game=smash4"}]},{"InstanceId":"feabf7a0d58c4c56b1b3cc25ae7e7c95","Name":"Shadow Ball","OwnerId":31,"Owner":"Mewtwo","HitboxActive":"23- (6- From Charge)","FirstActionableFrame":"49 (32 From Charge)","BaseDamage":"-","Angle":"-","BaseKnockBackSetKnockback":"-","LandingLag":null,"AutoCancel":null,"KnockbackGrowth":"-","MoveType":"special","IsWeightDependent":false,"Game":"Smash4","Related":{"Smash4":{"Character":"http://api.kuroganehammer.com/api/characters/name/Mewtwo?game=smash4","Self":"http://api.kuroganehammer.com/api/moves/feabf7a0d58c4c56b1b3cc25ae7e7c95?game=smash4"},"Ultimate":{"Character":"http://api.kuroganehammer.com/api/characters/name/Mewtwo?game=ultimate"}},"Links":[{"Rel":"self","Href":"http://api.kuroganehammer.com/api/moves/feabf7a0d58c4c56b1b3cc25ae7e7c95?game=smash4"},{"Rel":"character","Href":"http://api.kuroganehammer.com/api/characters/name/Mewtwo?game=smash4"}]},{"InstanceId":"f78eb9d8b84d4e91addee0aaab097280","Name":"Shadow Ball (Uncharged)","OwnerId":31,"Owner":"Mewtwo","HitboxActive":"-","FirstActionableFrame":"-","BaseDamage":"2.5","Angle":"361","BaseKnockBackSetKnockback":"14","LandingLag":null,"AutoCancel":null,"KnockbackGrowth":"30","MoveType":"special","IsWeightDependent":false,"Game":"Smash4","Related":{"Smash4":{"Character":"http://api.kuroganehammer.com/api/characters/name/Mewtwo?game=smash4","Self":"http://api.kuroganehammer.com/api/moves/f78eb9d8b84d4e91addee0aaab097280?game=smash4"},"Ultimate":{"Character":"http://api.kuroganehammer.com/api/characters/name/Mewtwo?game=ultimate"}},"Links":[{"Rel":"self","Href":"http://api.kuroganehammer.com/api/moves/f78eb9d8b84d4e91addee0aaab097280?game=smash4"},{"Rel":"character","Href":"http://api.kuroganehammer.com/api/characters/name/Mewtwo?game=smash4"}]},{"InstanceId":"b7310ea06d2043c6b40763d94971d30a","Name":"Shadow Ball (Charged)","OwnerId":31,"Owner":"Mewtwo","HitboxActive":"-","FirstActionableFrame":"-","BaseDamage":"25 (+3)","Angle":"47","BaseKnockBackSetKnockback":"30","LandingLag":null,"AutoCancel":null,"KnockbackGrowth":"67","MoveType":"special","IsWeightDependent":false,"Game":"Smash4","Related":{"Smash4":{"Character":"http://api.kuroganehammer.com/api/characters/name/Mewtwo?game=smash4","Self":"http://api.kuroganehammer.com/api/moves/b7310ea06d2043c6b40763d94971d30a?game=smash4"},"Ultimate":{"Character":"http://api.kuroganehammer.com/api/characters/name/Mewtwo?game=ultimate"}},"Links":[{"Rel":"self","Href":"http://api.kuroganehammer.com/api/moves/b7310ea06d2043c6b40763d94971d30a?game=smash4"},{"Rel":"character","Href":"http://api.kuroganehammer.com/api/characters/name/Mewtwo?game=smash4"}]},{"InstanceId":"5fe1d1e6aa8a45a498f75cabdc4b0319","Name":"Confusion","OwnerId":31,"Owner":"Mewtwo","HitboxActive":"12-15 (Reflects on: 12-35)","FirstActionableFrame":"45","BaseDamage":"1.15&#37;&#215;7, 1","Angle":"-","BaseKnockBackSetKnockback":"-","LandingLag":null,"AutoCancel":null,"KnockbackGrowth":"-","MoveType":"special","IsWeightDependent":false,"Game":"Smash4","Related":{"Smash4":{"Character":"http://api.kuroganehammer.com/api/characters/name/Mewtwo?game=smash4","Self":"http://api.kuroganehammer.com/api/moves/5fe1d1e6aa8a45a498f75cabdc4b0319?game=smash4"},"Ultimate":{"Character":"http://api.kuroganehammer.com/api/characters/name/Mewtwo?game=ultimate"}},"Links":[{"Rel":"self","Href":"http://api.kuroganehammer.com/api/moves/5fe1d1e6aa8a45a498f75cabdc4b0319?game=smash4"},{"Rel":"character","Href":"http://api.kuroganehammer.com/api/characters/name/Mewtwo?game=smash4"}]},{"InstanceId":"e9b5e216214b4305a666735dd9b20be6","Name":"Teleport","OwnerId":31,"Owner":"Mewtwo","HitboxActive":"Intangible: 9-17","FirstActionableFrame":"-","BaseDamage":"-","Angle":"-","BaseKnockBackSetKnockback":"-","LandingLag":null,"AutoCancel":null,"KnockbackGrowth":"-","MoveType":"special","IsWeightDependent":false,"Game":"Smash4","Related":{"Smash4":{"Character":"http://api.kuroganehammer.com/api/characters/name/Mewtwo?game=smash4","Self":"http://api.kuroganehammer.com/api/moves/e9b5e216214b4305a666735dd9b20be6?game=smash4"},"Ultimate":{"Character":"http://api.kuroganehammer.com/api/characters/name/Mewtwo?game=ultimate"}},"Links":[{"Rel":"self","Href":"http://api.kuroganehammer.com/api/moves/e9b5e216214b4305a666735dd9b20be6?game=smash4"},{"Rel":"character","Href":"http://api.kuroganehammer.com/api/characters/name/Mewtwo?game=smash4"}]},{"InstanceId":"3e0bfbc8dae74293913b61d51641c802","Name":"Disable","OwnerId":31,"Owner":"Mewtwo","HitboxActive":"16-22","FirstActionableFrame":"48","BaseDamage":"1","Angle":"-","BaseKnockBackSetKnockback":"-","LandingLag":null,"AutoCancel":null,"KnockbackGrowth":"-","MoveType":"special","IsWeightDependent":false,"Game":"Smash4","Related":{"Smash4":{"Character":"http://api.kuroganehammer.com/api/characters/name/Mewtwo?game=smash4","Self":"http://api.kuroganehammer.com/api/moves/3e0bfbc8dae74293913b61d51641c802?game=smash4"},"Ultimate":{"Character":"http://api.kuroganehammer.com/api/characters/name/Mewtwo?game=ultimate"}},"Links":[{"Rel":"self","Href":"http://api.kuroganehammer.com/api/moves/3e0bfbc8dae74293913b61d51641c802?game=smash4"},{"Rel":"character","Href":"http://api.kuroganehammer.com/api/characters/name/Mewtwo?game=smash4"}]},{"InstanceId":"618ed5a38f4c4213b02deede1f1d63d2","Name":"Fthrow","OwnerId":31,"Owner":"Mewtwo","HitboxActive":null,"FirstActionableFrame":null,"BaseDamage":"3, 2&#37;&#215;5","Angle":"-","BaseKnockBackSetKnockback":"-","LandingLag":null,"AutoCancel":null,"KnockbackGrowth":"-","MoveType":"throw","IsWeightDependent":true,"Game":"Smash4","Related":{"Smash4":{"Character":"http://api.kuroganehammer.com/api/characters/name/Mewtwo?game=smash4","Self":"http://api.kuroganehammer.com/api/moves/618ed5a38f4c4213b02deede1f1d63d2?game=smash4"},"Ultimate":{"Character":"http://api.kuroganehammer.com/api/characters/name/Mewtwo?game=ultimate"}},"Links":[{"Rel":"self","Href":"http://api.kuroganehammer.com/api/moves/618ed5a38f4c4213b02deede1f1d63d2?game=smash4"},{"Rel":"character","Href":"http://api.kuroganehammer.com/api/characters/name/Mewtwo?game=smash4"}]},{"InstanceId":"503a015180e14134a7d4b45b453a53f9","Name":"Bthrow","OwnerId":31,"Owner":"Mewtwo","HitboxActive":null,"FirstActionableFrame":null,"BaseDamage":"10","Angle":"47","BaseKnockBackSetKnockback":"70","LandingLag":null,"AutoCancel":null,"KnockbackGrowth":"75","MoveType":"throw","IsWeightDependent":true,"Game":"Smash4","Related":{"Smash4":{"Character":"http://api.kuroganehammer.com/api/characters/name/Mewtwo?game=smash4","Self":"http://api.kuroganehammer.com/api/moves/503a015180e14134a7d4b45b453a53f9?game=smash4"},"Ultimate":{"Character":"http://api.kuroganehammer.com/api/characters/name/Mewtwo?game=ultimate"}},"Links":[{"Rel":"self","Href":"http://api.kuroganehammer.com/api/moves/503a015180e14134a7d4b45b453a53f9?game=smash4"},{"Rel":"character","Href":"http://api.kuroganehammer.com/api/characters/name/Mewtwo?game=smash4"}]},{"InstanceId":"6e4d95ad15a745cbb5535051d8cd3e37","Name":"Uthrow","OwnerId":31,"Owner":"Mewtwo","HitboxActive":null,"FirstActionableFrame":null,"BaseDamage":"12","Angle":"90","BaseKnockBackSetKnockback":"72","LandingLag":null,"AutoCancel":null,"KnockbackGrowth":"65","MoveType":"throw","IsWeightDependent":true,"Game":"Smash4","Related":{"Smash4":{"Character":"http://api.kuroganehammer.com/api/characters/name/Mewtwo?game=smash4","Self":"http://api.kuroganehammer.com/api/moves/6e4d95ad15a745cbb5535051d8cd3e37?game=smash4"},"Ultimate":{"Character":"http://api.kuroganehammer.com/api/characters/name/Mewtwo?game=ultimate"}},"Links":[{"Rel":"self","Href":"http://api.kuroganehammer.com/api/moves/6e4d95ad15a745cbb5535051d8cd3e37?game=smash4"},{"Rel":"character","Href":"http://api.kuroganehammer.com/api/characters/name/Mewtwo?game=smash4"}]},{"InstanceId":"1cbd11282e934c2291d80020dbb8d2b3","Name":"Dthrow","OwnerId":31,"Owner":"Mewtwo","HitboxActive":null,"FirstActionableFrame":null,"BaseDamage":"4, 5","Angle":"74","BaseKnockBackSetKnockback":"65","LandingLag":null,"AutoCancel":null,"KnockbackGrowth":"50","MoveType":"throw","IsWeightDependent":false,"Game":"Smash4","Related":{"Smash4":{"Character":"http://api.kuroganehammer.com/api/characters/name/Mewtwo?game=smash4","Self":"http://api.kuroganehammer.com/api/moves/1cbd11282e934c2291d80020dbb8d2b3?game=smash4"},"Ultimate":{"Character":"http://api.kuroganehammer.com/api/characters/name/Mewtwo?game=ultimate"}},"Links":[{"Rel":"self","Href":"http://api.kuroganehammer.com/api/moves/1cbd11282e934c2291d80020dbb8d2b3?game=smash4"},{"Rel":"character","Href":"http://api.kuroganehammer.com/api/characters/name/Mewtwo?game=smash4"}]}]