[{"InstanceId":"9d58c0ef318d4e6098ffd1d48ab94194","Name":"Jab 1","OwnerId":52,"Owner":"ToonLink","HitboxActive":"6-7","FirstActionableFrame":"20","BaseDamage":"3","Angle":"50/80/88","BaseKnockBackSetKnockback":"35/25/W: 26","LandingLag":null,"AutoCancel":null,"KnockbackGrowth":"34/34/100","MoveType":"ground","IsWeightDependent":false,"Game":"Smash4","Related":{"Smash4":{"Character":"http://api.kuroganehammer.com/api/characters/name/ToonLink?game=smash4","Self":"http://api.kuroganehammer.com/api/moves/9d58c0ef318d4e6098ffd1d48ab94194?game=smash4"},"Ultimate":{"Character":"http://api.kuroganehammer.com/api/characters/name/ToonLink?game=ultimate"}},"Links":[{"Rel":"self","Href":"http://api.kuroganehammer.com/api/moves/9d58c0ef318d4e6098ffd1d48ab94194?game=smash4"},{"Rel":"character","Href":"http://api.kuroganehammer.com/api/characters/name/ToonLink?game=smash4"}]},{"InstanceId":"512b4e7dfa2a4208b0a1f355b53a527c","Name":"Jab 2","OwnerId":52,"Owner":"ToonLink","HitboxActive":"6-7","FirstActionableFrame":"21","BaseDamage":"2","Angle":"60/82/100","BaseKnockBackSetKnockback":"22","LandingLag":null,"AutoCancel":null,"KnockbackGrowth":"20","MoveType":"ground","IsWeightDependent":false,"Game":"Smash4","Related":{"Smash4":{"Character":"http://api.kuroganehammer.com/api/characters/name/ToonLink?game=smash4","Self":"http://api.kuroganehammer.com/api/moves/512b4e7dfa2a4208b0a1f355b53a527c?game=smash4"},"Ultimate":{"Character":"http://api.kuroganehammer.com/api/characters/name/ToonLink?game=ultimate"}},"Links":[{"Rel":"self","Href":"http://api.kuroganehammer.com/api/moves/512b4e7dfa2a4208b0a1f355b53a527c?game=smash4"},{"Rel":"character","Href":"http://api.kuroganehammer.com/api/characters/name/ToonLink?game=smash4"}]},{"InstanceId":"1570394282c14e2f91ddf684dfd50863","Name":"Jab 3","OwnerId":52,"Owner":"ToonLink","HitboxActive":"6-10","FirstActionableFrame":"37","BaseDamage":"4","Angle":"48","BaseKnockBackSetKnockback":"55","LandingLag":null,"AutoCancel":null,"KnockbackGrowth":"100","MoveType":"ground","IsWeightDependent":false,"Game":"Smash4","Related":{"Smash4":{"Character":"http://api.kuroganehammer.com/api/characters/name/ToonLink?game=smash4","Self":"http://api.kuroganehammer.com/api/moves/1570394282c14e2f91ddf684dfd50863?game=smash4"},"Ultimate":{"Character":"http://api.kuroganehammer.com/api/characters/name/ToonLink?game=ultimate"}},"Links":[{"Rel":"self","Href":"http://api.kuroganehammer.com/api/moves/1570394282c14e2f91ddf684dfd50863?game=smash4"},{"Rel":"character","Href":"http://api.kuroganehammer.com/api/characters/name/ToonLink?game=smash4"}]},{"InstanceId":"58826549b3d041f59ef820cd0ac2e7d0","Name":"Dash Attack","OwnerId":52,"Owner":"ToonLink","HitboxActive":"9-11","FirstActionableFrame":"40","BaseDamage":"8/6/8","Angle":"65","BaseKnockBackSetKnockback":"70","LandingLag":null,"AutoCancel":null,"KnockbackGrowth":"70","MoveType":"ground","IsWeightDependent":false,"Game":"Smash4","Related":{"Smash4":{"Character":"http://api.kuroganehammer.com/api/characters/name/ToonLink?game=smash4","Self":"http://api.kuroganehammer.com/api/moves/58826549b3d041f59ef820cd0ac2e7d0?game=smash4"},"Ultimate":{"Character":"http://api.kuroganehammer.com/api/characters/name/ToonLink?game=ultimate"}},"Links":[{"Rel":"self","Href":"http://api.kuroganehammer.com/api/moves/58826549b3d041f59ef820cd0ac2e7d0?game=smash4"},{"Rel":"character","Href":"http://api.kuroganehammer.com/api/characters/name/ToonLink?game=smash4"}]},{"InstanceId":"89d6de2cdd2a44a39c6e3943e7574b12","Name":"Ftilt","OwnerId":52,"Owner":"ToonLink","HitboxActive":"9-13","FirstActionableFrame":"34","BaseDamage":"9","Angle":"361/20/20","BaseKnockBackSetKnockback":"25","LandingLag":null,"AutoCancel":null,"KnockbackGrowth":"102","MoveType":"ground","IsWeightDependent":false,"Game":"Smash4","Related":{"Smash4":{"Character":"http://api.kuroganehammer.com/api/characters/name/ToonLink?game=smash4","Self":"http://api.kuroganehammer.com/api/moves/89d6de2cdd2a44a39c6e3943e7574b12?game=smash4"},"Ultimate":{"Character":"http://api.kuroganehammer.com/api/characters/name/ToonLink?game=ultimate"}},"Links":[{"Rel":"self","Href":"http://api.kuroganehammer.com/api/moves/89d6de2cdd2a44a39c6e3943e7574b12?game=smash4"},{"Rel":"character","Href":"http://api.kuroganehammer.com/api/characters/name/ToonLink?game=smash4"}]},{"InstanceId":"24889916041e477e8ceedbcc1ab42198","Name":"Utilt","OwnerId":52,"Owner":"ToonLink","HitboxActive":"8-12","FirstActionableFrame":"26","BaseDamage":"5","Angle":"95/85/105","BaseKnockBackSetKnockback":"30","LandingLag":null,"AutoCancel":null,"KnockbackGrowth":"140","MoveType":"ground","IsWeightDependent":false,"Game":"Smash4","Related":{"Smash4":{"Character":"http://api.kuroganehammer.com/api/characters/name/ToonLink?game=smash4","Self":"http://api.kuroganehammer.com/api/moves/24889916041e477e8ceedbcc1ab42198?game=smash4"},"Ultimate":{"Character":"http://api.kuroganehammer.com/api/characters/name/ToonLink?game=ultimate"}},"Links":[{"Rel":"self","Href":"http://api.kuroganehammer.com/api/moves/24889916041e477e8ceedbcc1ab42198?game=smash4"},{"Rel":"character","Href":"http://api.kuroganehammer.com/api/characters/name/ToonLink?game=smash4"}]},{"InstanceId":"e0d12f082a4244448df41ae233c4e81c","Name":"Dtilt","OwnerId":52,"Owner":"ToonLink","HitboxActive":"9-10","FirstActionableFrame":"23","BaseDamage":"7","Angle":"361","BaseKnockBackSetKnockback":"30","LandingLag":null,"AutoCancel":null,"KnockbackGrowth":"88","MoveType":"ground","IsWeightDependent":false,"Game":"Smash4","Related":{"Smash4":{"Character":"http://api.kuroganehammer.com/api/characters/name/ToonLink?game=smash4","Self":"http://api.kuroganehammer.com/api/moves/e0d12f082a4244448df41ae233c4e81c?game=smash4"},"Ultimate":{"Character":"http://api.kuroganehammer.com/api/characters/name/ToonLink?game=ultimate"}},"Links":[{"Rel":"self","Href":"http://api.kuroganehammer.com/api/moves/e0d12f082a4244448df41ae233c4e81c?game=smash4"},{"Rel":"character","Href":"http://api.kuroganehammer.com/api/characters/name/ToonLink?game=smash4"}]},{"InstanceId":"cc78aee0e08a4786b33a474185538253","Name":"Fsmash (Hit 1)","OwnerId":52,"Owner":"ToonLink","HitboxActive":"15-17","FirstActionableFrame":"49","BaseDamage":"10","Angle":"75/55/47/40","BaseKnockBackSetKnockback":"49/54/56/60","LandingLag":null,"AutoCancel":null,"KnockbackGrowth":"10","MoveType":"ground","IsWeightDependent":false,"Game":"Smash4","Related":{"Smash4":{"Character":"http://api.kuroganehammer.com/api/characters/name/ToonLink?game=smash4","Self":"http://api.kuroganehammer.com/api/moves/cc78aee0e08a4786b33a474185538253?game=smash4"},"Ultimate":{"Character":"http://api.kuroganehammer.com/api/characters/name/ToonLink?game=ultimate"}},"Links":[{"Rel":"self","Href":"http://api.kuroganehammer.com/api/moves/cc78aee0e08a4786b33a474185538253?game=smash4"},{"Rel":"character","Href":"http://api.kuroganehammer.com/api/characters/name/ToonLink?game=smash4"}]},{"InstanceId":"86a5fdd0e88a4f73aa04b3e4e3db1f3c","Name":"Fsmash (Hit 2)","OwnerId":52,"Owner":"ToonLink","HitboxActive":"12-14","FirstActionableFrame":"50","BaseDamage":"11","Angle":"40","BaseKnockBackSetKnockback":"32/32/25","LandingLag":null,"AutoCancel":null,"KnockbackGrowth":"130","MoveType":"ground","IsWeightDependent":false,"Game":"Smash4","Related":{"Smash4":{"Character":"http://api.kuroganehammer.com/api/characters/name/ToonLink?game=smash4","Self":"http://api.kuroganehammer.com/api/moves/86a5fdd0e88a4f73aa04b3e4e3db1f3c?game=smash4"},"Ultimate":{"Character":"http://api.kuroganehammer.com/api/characters/name/ToonLink?game=ultimate"}},"Links":[{"Rel":"self","Href":"http://api.kuroganehammer.com/api/moves/86a5fdd0e88a4f73aa04b3e4e3db1f3c?game=smash4"},{"Rel":"character","Href":"http://api.kuroganehammer.com/api/characters/name/ToonLink?game=smash4"}]},{"InstanceId":"8dd1a309b94743a884a90fe0384e0a57","Name":"Usmash (Early)","OwnerId":52,"Owner":"ToonLink","HitboxActive":"11","FirstActionableFrame":"43","BaseDamage":"13","Angle":"100/96/96","BaseKnockBackSetKnockback":"43","LandingLag":null,"AutoCancel":null,"KnockbackGrowth":"94","MoveType":"ground","IsWeightDependent":false,"Game":"Smash4","Related":{"Smash4":{"Character":"http://api.kuroganehammer.com/api/characters/name/ToonLink?game=smash4","Self":"http://api.kuroganehammer.com/api/moves/8dd1a309b94743a884a90fe0384e0a57?game=smash4"},"Ultimate":{"Character":"http://api.kuroganehammer.com/api/characters/name/ToonLink?game=ultimate"}},"Links":[{"Rel":"self","Href":"http://api.kuroganehammer.com/api/moves/8dd1a309b94743a884a90fe0384e0a57?game=smash4"},{"Rel":"character","Href":"http://api.kuroganehammer.com/api/characters/name/ToonLink?game=smash4"}]},{"InstanceId":"a411f7c2d66f449cae940e17391b4736","Name":"Usmash","OwnerId":52,"Owner":"ToonLink","HitboxActive":"12-13","FirstActionableFrame":"-","BaseDamage":"13","Angle":"96","BaseKnockBackSetKnockback":"30/43/43","LandingLag":null,"AutoCancel":null,"KnockbackGrowth":"93/94/94","MoveType":"ground","IsWeightDependent":false,"Game":"Smash4","Related":{"Smash4":{"Character":"http://api.kuroganehammer.com/api/characters/name/ToonLink?game=smash4","Self":"http://api.kuroganehammer.com/api/moves/a411f7c2d66f449cae940e17391b4736?game=smash4"},"Ultimate":{"Character":"http://api.kuroganehammer.com/api/characters/name/ToonLink?game=ultimate"}},"Links":[{"Rel":"self","Href":"http://api.kuroganehammer.com/api/moves/a411f7c2d66f449cae940e17391b4736?game=smash4"},{"Rel":"character","Href":"http://api.kuroganehammer.com/api/characters/name/ToonLink?game=smash4"}]},{"InstanceId":"07d6cf32add34dd7b7b1da01bb5b82e5","Name":"Usmash (Late)","OwnerId":52,"Owner":"ToonLink","HitboxActive":"14-17","FirstActionableFrame":"-","BaseDamage":"10","Angle":"96","BaseKnockBackSetKnockback":"30/43/43","LandingLag":null,"AutoCancel":null,"KnockbackGrowth":"93/94/94","MoveType":"ground","IsWeightDependent":false,"Game":"Smash4","Related":{"Smash4":{"Character":"http://api.kuroganehammer.com/api/characters/name/ToonLink?game=smash4","Self":"http://api.kuroganehammer.com/api/moves/07d6cf32add34dd7b7b1da01bb5b82e5?game=smash4"},"Ultimate":{"Character":"http://api.kuroganehammer.com/api/characters/name/ToonLink?game=ultimate"}},"Links":[{"Rel":"self","Href":"http://api.kuroganehammer.com/api/moves/07d6cf32add34dd7b7b1da01bb5b82e5?game=smash4"},{"Rel":"character","Href":"http://api.kuroganehammer.com/api/characters/name/ToonLink?game=smash4"}]},{"InstanceId":"73b414a065b9419a81b0a8adc1f23ec9","Name":"Dsmash (Hit 1)","OwnerId":52,"Owner":"ToonLink","HitboxActive":"9-10","FirstActionableFrame":"50","BaseDamage":"7/6/6","Angle":"70/170/168","BaseKnockBackSetKnockback":"40/W: 60/120","LandingLag":null,"AutoCancel":null,"KnockbackGrowth":"100","MoveType":"ground","IsWeightDependent":false,"Game":"Smash4","Related":{"Smash4":{"Character":"http://api.kuroganehammer.com/api/characters/name/ToonLink?game=smash4","Self":"http://api.kuroganehammer.com/api/moves/73b414a065b9419a81b0a8adc1f23ec9?game=smash4"},"Ultimate":{"Character":"http://api.kuroganehammer.com/api/characters/name/ToonLink?game=ultimate"}},"Links":[{"Rel":"self","Href":"http://api.kuroganehammer.com/api/moves/73b414a065b9419a81b0a8adc1f23ec9?game=smash4"},{"Rel":"character","Href":"http://api.kuroganehammer.com/api/characters/name/ToonLink?game=smash4"}]},{"InstanceId":"5ef38dbc5bfd4773869f8f8694483af5","Name":"Dsmash (Hit 2)","OwnerId":52,"Owner":"ToonLink","HitboxActive":"17-18","FirstActionableFrame":"-","BaseDamage":"7/6","Angle":"50","BaseKnockBackSetKnockback":"60","LandingLag":null,"AutoCancel":null,"KnockbackGrowth":"127","MoveType":"ground","IsWeightDependent":false,"Game":"Smash4","Related":{"Smash4":{"Character":"http://api.kuroganehammer.com/api/characters/name/ToonLink?game=smash4","Self":"http://api.kuroganehammer.com/api/moves/5ef38dbc5bfd4773869f8f8694483af5?game=smash4"},"Ultimate":{"Character":"http://api.kuroganehammer.com/api/characters/name/ToonLink?game=ultimate"}},"Links":[{"Rel":"self","Href":"http://api.kuroganehammer.com/api/moves/5ef38dbc5bfd4773869f8f8694483af5?game=smash4"},{"Rel":"character","Href":"http://api.kuroganehammer.com/api/characters/name/ToonLink?game=smash4"}]},{"InstanceId":"03f80b77675641ccacd164ba876479d4","Name":"Standing Grab","OwnerId":52,"Owner":"ToonLink","HitboxActive":"12-18","FirstActionableFrame":"62","BaseDamage":"","Angle":"","BaseKnockBackSetKnockback":"","LandingLag":null,"AutoCancel":null,"KnockbackGrowth":"","MoveType":"ground","IsWeightDependent":false,"Game":"Smash4","Related":{"Smash4":{"Character":"http://api.kuroganehammer.com/api/characters/name/ToonLink?game=smash4","Self":"http://api.kuroganehammer.com/api/moves/03f80b77675641ccacd164ba876479d4?game=smash4"},"Ultimate":{"Character":"http://api.kuroganehammer.com/api/characters/name/ToonLink?game=ultimate"}},"Links":[{"Rel":"self","Href":"http://api.kuroganehammer.com/api/moves/03f80b77675641ccacd164ba876479d4?game=smash4"},{"Rel":"character","Href":"http://api.kuroganehammer.com/api/characters/name/ToonLink?game=smash4"}]},{"InstanceId":"ecf8d79046184f80bf1e879cdac5677e","Name":"Dash Grab","OwnerId":52,"Owner":"ToonLink","HitboxActive":"14-20","FirstActionableFrame":"72","BaseDamage":"","Angle":"","BaseKnockBackSetKnockback":"","LandingLag":null,"AutoCancel":null,"KnockbackGrowth":"","MoveType":"ground","IsWeightDependent":false,"Game":"Smash4","Related":{"Smash4":{"Character":"http://api.kuroganehammer.com/api/characters/name/ToonLink?game=smash4","Self":"http://api.kuroganehammer.com/api/moves/ecf8d79046184f80bf1e879cdac5677e?game=smash4"},"Ultimate":{"Character":"http://api.kuroganehammer.com/api/characters/name/ToonLink?game=ultimate"}},"Links":[{"Rel":"self","Href":"http://api.kuroganehammer.com/api/moves/ecf8d79046184f80bf1e879cdac5677e?game=smash4"},{"Rel":"character","Href":"http://api.kuroganehammer.com/api/characters/name/ToonLink?game=smash4"}]},{"InstanceId":"d2457173ff944eceacfba188353bf15e","Name":"Pivot Grab","OwnerId":52,"Owner":"ToonLink","HitboxActive":"15-21","FirstActionableFrame":"72","BaseDamage":"","Angle":"","BaseKnockBackSetKnockback":"","LandingLag":null,"AutoCancel":null,"KnockbackGrowth":"","MoveType":"ground","IsWeightDependent":false,"Game":"Smash4","Related":{"Smash4":{"Character":"http://api.kuroganehammer.com/api/characters/name/ToonLink?game=smash4","Self":"http://api.kuroganehammer.com/api/moves/d2457173ff944eceacfba188353bf15e?game=smash4"},"Ultimate":{"Character":"http://api.kuroganehammer.com/api/characters/name/ToonLink?game=ultimate"}},"Links":[{"Rel":"self","Href":"http://api.kuroganehammer.com/api/moves/d2457173ff944eceacfba188353bf15e?game=smash4"},{"Rel":"character","Href":"http://api.kuroganehammer.com/api/characters/name/ToonLink?game=smash4"}]},{"InstanceId":"954f547b1d8047dd9a58dbbcae35af66","Name":"Spotdodge","OwnerId":52,"Owner":"ToonLink","HitboxActive":"2-15","FirstActionableFrame":"25","BaseDamage":"","Angle":"","BaseKnockBackSetKnockback":"","LandingLag":null,"AutoCancel":null,"KnockbackGrowth":"","MoveType":"ground","IsWeightDependent":false,"Game":"Smash4","Related":{"Smash4":{"Character":"http://api.kuroganehammer.com/api/characters/name/ToonLink?game=smash4","Self":"http://api.kuroganehammer.com/api/moves/954f547b1d8047dd9a58dbbcae35af66?game=smash4"},"Ultimate":{"Character":"http://api.kuroganehammer.com/api/characters/name/ToonLink?game=ultimate"}},"Links":[{"Rel":"self","Href":"http://api.kuroganehammer.com/api/moves/954f547b1d8047dd9a58dbbcae35af66?game=smash4"},{"Rel":"character","Href":"http://api.kuroganehammer.com/api/characters/name/ToonLink?game=smash4"}]},{"InstanceId":"883ccf9306554c7c85e150427a1491d8","Name":"Forward Roll","OwnerId":52,"Owner":"ToonLink","HitboxActive":"4-14","FirstActionableFrame":"27","BaseDamage":"","Angle":"","BaseKnockBackSetKnockback":"","LandingLag":null,"AutoCancel":null,"KnockbackGrowth":"","MoveType":"ground","IsWeightDependent":false,"Game":"Smash4","Related":{"Smash4":{"Character":"http://api.kuroganehammer.com/api/characters/name/ToonLink?game=smash4","Self":"http://api.kuroganehammer.com/api/moves/883ccf9306554c7c85e150427a1491d8?game=smash4"},"Ultimate":{"Character":"http://api.kuroganehammer.com/api/characters/name/ToonLink?game=ultimate"}},"Links":[{"Rel":"self","Href":"http://api.kuroganehammer.com/api/moves/883ccf9306554c7c85e150427a1491d8?game=smash4"},{"Rel":"character","Href":"http://api.kuroganehammer.com/api/characters/name/ToonLink?game=smash4"}]},{"InstanceId":"32d6cd9efb724d61a5dcc29bfd999331","Name":"Back Roll","OwnerId":52,"Owner":"ToonLink","HitboxActive":"4-14","FirstActionableFrame":"27","BaseDamage":"","Angle":"","BaseKnockBackSetKnockback":"","LandingLag":null,"AutoCancel":null,"KnockbackGrowth":"","MoveType":"ground","IsWeightDependent":false,"Game":"Smash4","Related":{"Smash4":{"Character":"http://api.kuroganehammer.com/api/characters/name/ToonLink?game=smash4","Self":"http://api.kuroganehammer.com/api/moves/32d6cd9efb724d61a5dcc29bfd999331?game=smash4"},"Ultimate":{"Character":"http://api.kuroganehammer.com/api/characters/name/ToonLink?game=ultimate"}},"Links":[{"Rel":"self","Href":"http://api.kuroganehammer.com/api/moves/32d6cd9efb724d61a5dcc29bfd999331?game=smash4"},{"Rel":"character","Href":"http://api.kuroganehammer.com/api/characters/name/ToonLink?game=smash4"}]},{"InstanceId":"41b32ea52e8c4c4cbe7db67e98d5f2fd","Name":"Airdodge","OwnerId":52,"Owner":"ToonLink","HitboxActive":"2-25","FirstActionableFrame":"31","BaseDamage":"","Angle":"","BaseKnockBackSetKnockback":"","LandingLag":null,"AutoCancel":null,"KnockbackGrowth":"","MoveType":"ground","IsWeightDependent":false,"Game":"Smash4","Related":{"Smash4":{"Character":"http://api.kuroganehammer.com/api/characters/name/ToonLink?game=smash4","Self":"http://api.kuroganehammer.com/api/moves/41b32ea52e8c4c4cbe7db67e98d5f2fd?game=smash4"},"Ultimate":{"Character":"http://api.kuroganehammer.com/api/characters/name/ToonLink?game=ultimate"}},"Links":[{"Rel":"self","Href":"http://api.kuroganehammer.com/api/moves/41b32ea52e8c4c4cbe7db67e98d5f2fd?game=smash4"},{"Rel":"character","Href":"http://api.kuroganehammer.com/api/characters/name/ToonLink?game=smash4"}]},{"InstanceId":"c51486d20f854d44b18fd21db0eebbe3","Name":"Nair (Hit 1)","OwnerId":52,"Owner":"ToonLink","HitboxActive":"6-7","FirstActionableFrame":"42","BaseDamage":"8.5","Angle":"361","BaseKnockBackSetKnockback":"20","LandingLag":"12","AutoCancel":"1-2, 41>","KnockbackGrowth":"100","MoveType":"aerial","IsWeightDependent":false,"Game":"Smash4","Related":{"Smash4":{"Character":"http://api.kuroganehammer.com/api/characters/name/ToonLink?game=smash4","Self":"http://api.kuroganehammer.com/api/moves/c51486d20f854d44b18fd21db0eebbe3?game=smash4"},"Ultimate":{"Character":"http://api.kuroganehammer.com/api/characters/name/ToonLink?game=ultimate"}},"Links":[{"Rel":"self","Href":"http://api.kuroganehammer.com/api/moves/c51486d20f854d44b18fd21db0eebbe3?game=smash4"},{"Rel":"character","Href":"http://api.kuroganehammer.com/api/characters/name/ToonLink?game=smash4"}]},{"InstanceId":"35fc9e28dd184cf183437c204fb03437","Name":"Nair (Hit 2)","OwnerId":52,"Owner":"ToonLink","HitboxActive":"13-14","FirstActionableFrame":"-","BaseDamage":"7","Angle":"361","BaseKnockBackSetKnockback":"20","LandingLag":"-","AutoCancel":"-","KnockbackGrowth":"100","MoveType":"aerial","IsWeightDependent":false,"Game":"Smash4","Related":{"Smash4":{"Character":"http://api.kuroganehammer.com/api/characters/name/ToonLink?game=smash4","Self":"http://api.kuroganehammer.com/api/moves/35fc9e28dd184cf183437c204fb03437?game=smash4"},"Ultimate":{"Character":"http://api.kuroganehammer.com/api/characters/name/ToonLink?game=ultimate"}},"Links":[{"Rel":"self","Href":"http://api.kuroganehammer.com/api/moves/35fc9e28dd184cf183437c204fb03437?game=smash4"},{"Rel":"character","Href":"http://api.kuroganehammer.com/api/characters/name/ToonLink?game=smash4"}]},{"InstanceId":"c272f2274929457f8c1b0576e943dd75","Name":"Fair","OwnerId":52,"Owner":"ToonLink","HitboxActive":"14-15","FirstActionableFrame":"39","BaseDamage":"13","Angle":"361","BaseKnockBackSetKnockback":"35","LandingLag":"18","AutoCancel":"1-3, 51>","KnockbackGrowth":"98","MoveType":"aerial","IsWeightDependent":false,"Game":"Smash4","Related":{"Smash4":{"Character":"http://api.kuroganehammer.com/api/characters/name/ToonLink?game=smash4","Self":"http://api.kuroganehammer.com/api/moves/c272f2274929457f8c1b0576e943dd75?game=smash4"},"Ultimate":{"Character":"http://api.kuroganehammer.com/api/characters/name/ToonLink?game=ultimate"}},"Links":[{"Rel":"self","Href":"http://api.kuroganehammer.com/api/moves/c272f2274929457f8c1b0576e943dd75?game=smash4"},{"Rel":"character","Href":"http://api.kuroganehammer.com/api/characters/name/ToonLink?game=smash4"}]},{"InstanceId":"e00e017b778648339232616a8674844b","Name":"Bair","OwnerId":52,"Owner":"ToonLink","HitboxActive":"7-9","FirstActionableFrame":"46","BaseDamage":"11","Angle":"60","BaseKnockBackSetKnockback":"18","LandingLag":"17","AutoCancel":"38>","KnockbackGrowth":"117","MoveType":"aerial","IsWeightDependent":false,"Game":"Smash4","Related":{"Smash4":{"Character":"http://api.kuroganehammer.com/api/characters/name/ToonLink?game=smash4","Self":"http://api.kuroganehammer.com/api/moves/e00e017b778648339232616a8674844b?game=smash4"},"Ultimate":{"Character":"http://api.kuroganehammer.com/api/characters/name/ToonLink?game=ultimate"}},"Links":[{"Rel":"self","Href":"http://api.kuroganehammer.com/api/moves/e00e017b778648339232616a8674844b?game=smash4"},{"Rel":"character","Href":"http://api.kuroganehammer.com/api/characters/name/ToonLink?game=smash4"}]},{"InstanceId":"f43bde2a40e045b2b81cb17d225f2272","Name":"Uair","OwnerId":52,"Owner":"ToonLink","HitboxActive":"11-13","FirstActionableFrame":"60","BaseDamage":"14","Angle":"80","BaseKnockBackSetKnockback":"25","LandingLag":"21","AutoCancel":"1-5, 47>","KnockbackGrowth":"95","MoveType":"aerial","IsWeightDependent":false,"Game":"Smash4","Related":{"Smash4":{"Character":"http://api.kuroganehammer.com/api/characters/name/ToonLink?game=smash4","Self":"http://api.kuroganehammer.com/api/moves/f43bde2a40e045b2b81cb17d225f2272?game=smash4"},"Ultimate":{"Character":"http://api.kuroganehammer.com/api/characters/name/ToonLink?game=ultimate"}},"Links":[{"Rel":"self","Href":"http://api.kuroganehammer.com/api/moves/f43bde2a40e045b2b81cb17d225f2272?game=smash4"},{"Rel":"character","Href":"http://api.kuroganehammer.com/api/characters/name/ToonLink?game=smash4"}]},{"InstanceId":"8a643329eccd40909614b6fa5ef80ed8","Name":"Uair (Late)","OwnerId":52,"Owner":"ToonLink","HitboxActive":"14-40","FirstActionableFrame":"-","BaseDamage":"11","Angle":"80","BaseKnockBackSetKnockback":"25","LandingLag":"-","AutoCancel":"-","KnockbackGrowth":"95","MoveType":"aerial","IsWeightDependent":false,"Game":"Smash4","Related":{"Smash4":{"Character":"http://api.kuroganehammer.com/api/characters/name/ToonLink?game=smash4","Self":"http://api.kuroganehammer.com/api/moves/8a643329eccd40909614b6fa5ef80ed8?game=smash4"},"Ultimate":{"Character":"http://api.kuroganehammer.com/api/characters/name/ToonLink?game=ultimate"}},"Links":[{"Rel":"self","Href":"http://api.kuroganehammer.com/api/moves/8a643329eccd40909614b6fa5ef80ed8?game=smash4"},{"Rel":"character","Href":"http://api.kuroganehammer.com/api/characters/name/ToonLink?game=smash4"}]},{"InstanceId":"4dc97ddfff7d4116bca13164f48424c4","Name":"Dair","OwnerId":52,"Owner":"ToonLink","HitboxActive":"17-25","FirstActionableFrame":"80","BaseDamage":"16","Angle":"268","BaseKnockBackSetKnockback":"40","LandingLag":"40","AutoCancel":"1-5, 65>","KnockbackGrowth":"80","MoveType":"aerial","IsWeightDependent":false,"Game":"Smash4","Related":{"Smash4":{"Character":"http://api.kuroganehammer.com/api/characters/name/ToonLink?game=smash4","Self":"http://api.kuroganehammer.com/api/moves/4dc97ddfff7d4116bca13164f48424c4?game=smash4"},"Ultimate":{"Character":"http://api.kuroganehammer.com/api/characters/name/ToonLink?game=ultimate"}},"Links":[{"Rel":"self","Href":"http://api.kuroganehammer.com/api/moves/4dc97ddfff7d4116bca13164f48424c4?game=smash4"},{"Rel":"character","Href":"http://api.kuroganehammer.com/api/characters/name/ToonLink?game=smash4"}]},{"InstanceId":"e360a0a161a64a8389cad6453d27c584","Name":"Dair (Late)","OwnerId":52,"Owner":"ToonLink","HitboxActive":"26-64","FirstActionableFrame":"-","BaseDamage":"12","Angle":"50","BaseKnockBackSetKnockback":"40","LandingLag":"-","AutoCancel":"-","KnockbackGrowth":"100","MoveType":"aerial","IsWeightDependent":false,"Game":"Smash4","Related":{"Smash4":{"Character":"http://api.kuroganehammer.com/api/characters/name/ToonLink?game=smash4","Self":"http://api.kuroganehammer.com/api/moves/e360a0a161a64a8389cad6453d27c584?game=smash4"},"Ultimate":{"Character":"http://api.kuroganehammer.com/api/characters/name/ToonLink?game=ultimate"}},"Links":[{"Rel":"self","Href":"http://api.kuroganehammer.com/api/moves/e360a0a161a64a8389cad6453d27c584?game=smash4"},{"Rel":"character","Href":"http://api.kuroganehammer.com/api/characters/name/ToonLink?game=smash4"}]},{"InstanceId":"22f1b96514dd445a850cb5cb22baacf5","Name":"Dair (Landing)","OwnerId":52,"Owner":"ToonLink","HitboxActive":"1-4","FirstActionableFrame":"-","BaseDamage":"5","Angle":"30","BaseKnockBackSetKnockback":"20","LandingLag":"-","AutoCancel":"-","KnockbackGrowth":"100","MoveType":"aerial","IsWeightDependent":false,"Game":"Smash4","Related":{"Smash4":{"Character":"http://api.kuroganehammer.com/api/characters/name/ToonLink?game=smash4","Self":"http://api.kuroganehammer.com/api/moves/22f1b96514dd445a850cb5cb22baacf5?game=smash4"},"Ultimate":{"Character":"http://api.kuroganehammer.com/api/characters/name/ToonLink?game=ultimate"}},"Links":[{"Rel":"self","Href":"http://api.kuroganehammer.com/api/moves/22f1b96514dd445a850cb5cb22baacf5?game=smash4"},{"Rel":"character","Href":"http://api.kuroganehammer.com/api/characters/name/ToonLink?game=smash4"}]},{"InstanceId":"fb0158a2195f48b5a659f111b92089cd","Name":"Dair (Landing, Windbox)","OwnerId":52,"Owner":"ToonLink","HitboxActive":"1 (Ground Only)","FirstActionableFrame":"-","BaseDamage":"0","Angle":"0","BaseKnockBackSetKnockback":"W: 58/35","LandingLag":"-","AutoCancel":"-","KnockbackGrowth":"100","MoveType":"aerial","IsWeightDependent":false,"Game":"Smash4","Related":{"Smash4":{"Character":"http://api.kuroganehammer.com/api/characters/name/ToonLink?game=smash4","Self":"http://api.kuroganehammer.com/api/moves/fb0158a2195f48b5a659f111b92089cd?game=smash4"},"Ultimate":{"Character":"http://api.kuroganehammer.com/api/characters/name/ToonLink?game=ultimate"}},"Links":[{"Rel":"self","Href":"http://api.kuroganehammer.com/api/moves/fb0158a2195f48b5a659f111b92089cd?game=smash4"},{"Rel":"character","Href":"http://api.kuroganehammer.com/api/characters/name/ToonLink?game=smash4"}]},{"InstanceId":"c9a8debec7ab485cb5334a7d45f48969","Name":"Zair","OwnerId":52,"Owner":"ToonLink","HitboxActive":"11-20","FirstActionableFrame":"75","BaseDamage":"4","Angle":"45","BaseKnockBackSetKnockback":"60","LandingLag":"8","AutoCancel":"-","KnockbackGrowth":"30","MoveType":"aerial","IsWeightDependent":false,"Game":"Smash4","Related":{"Smash4":{"Character":"http://api.kuroganehammer.com/api/characters/name/ToonLink?game=smash4","Self":"http://api.kuroganehammer.com/api/moves/c9a8debec7ab485cb5334a7d45f48969?game=smash4"},"Ultimate":{"Character":"http://api.kuroganehammer.com/api/characters/name/ToonLink?game=ultimate"}},"Links":[{"Rel":"self","Href":"http://api.kuroganehammer.com/api/moves/c9a8debec7ab485cb5334a7d45f48969?game=smash4"},{"Rel":"character","Href":"http://api.kuroganehammer.com/api/characters/name/ToonLink?game=smash4"}]},{"InstanceId":"e4de8bf1ffed4685a237beecee43a7e1","Name":"Hero's Bow (No Charge)","OwnerId":52,"Owner":"ToonLink","HitboxActive":"18-","FirstActionableFrame":"42","BaseDamage":"4","Angle":"361","BaseKnockBackSetKnockback":"8","LandingLag":null,"AutoCancel":null,"KnockbackGrowth":"50","MoveType":"special","IsWeightDependent":false,"Game":"Smash4","Related":{"Smash4":{"Character":"http://api.kuroganehammer.com/api/characters/name/ToonLink?game=smash4","Self":"http://api.kuroganehammer.com/api/moves/e4de8bf1ffed4685a237beecee43a7e1?game=smash4"},"Ultimate":{"Character":"http://api.kuroganehammer.com/api/characters/name/ToonLink?game=ultimate"}},"Links":[{"Rel":"self","Href":"http://api.kuroganehammer.com/api/moves/e4de8bf1ffed4685a237beecee43a7e1?game=smash4"},{"Rel":"character","Href":"http://api.kuroganehammer.com/api/characters/name/ToonLink?game=smash4"}]},{"InstanceId":"87ed3b6234c446c18619eaaddc86b2f5","Name":"Hero's Bow (Full Charge)","OwnerId":52,"Owner":"ToonLink","HitboxActive":"61-","FirstActionableFrame":"85","BaseDamage":"5","Angle":"361","BaseKnockBackSetKnockback":"8","LandingLag":null,"AutoCancel":null,"KnockbackGrowth":"50","MoveType":"special","IsWeightDependent":false,"Game":"Smash4","Related":{"Smash4":{"Character":"http://api.kuroganehammer.com/api/characters/name/ToonLink?game=smash4","Self":"http://api.kuroganehammer.com/api/moves/87ed3b6234c446c18619eaaddc86b2f5?game=smash4"},"Ultimate":{"Character":"http://api.kuroganehammer.com/api/characters/name/ToonLink?game=ultimate"}},"Links":[{"Rel":"self","Href":"http://api.kuroganehammer.com/api/moves/87ed3b6234c446c18619eaaddc86b2f5?game=smash4"},{"Rel":"character","Href":"http://api.kuroganehammer.com/api/characters/name/ToonLink?game=smash4"}]},{"InstanceId":"8e3fb923ff4c4ac68d66c0dd79afbcd5","Name":"Boomerang","OwnerId":52,"Owner":"ToonLink","HitboxActive":"27-35","FirstActionableFrame":"46","BaseDamage":"8","Angle":"70","BaseKnockBackSetKnockback":"50","LandingLag":null,"AutoCancel":null,"KnockbackGrowth":"50","MoveType":"special","IsWeightDependent":false,"Game":"Smash4","Related":{"Smash4":{"Character":"http://api.kuroganehammer.com/api/characters/name/ToonLink?game=smash4","Self":"http://api.kuroganehammer.com/api/moves/8e3fb923ff4c4ac68d66c0dd79afbcd5?game=smash4"},"Ultimate":{"Character":"http://api.kuroganehammer.com/api/characters/name/ToonLink?game=ultimate"}},"Links":[{"Rel":"self","Href":"http://api.kuroganehammer.com/api/moves/8e3fb923ff4c4ac68d66c0dd79afbcd5?game=smash4"},{"Rel":"character","Href":"http://api.kuroganehammer.com/api/characters/name/ToonLink?game=smash4"}]},{"InstanceId":"ace9b0929d5647c7a5a09a5f12646d23","Name":"Boomerang (Late)","OwnerId":52,"Owner":"ToonLink","HitboxActive":"36-","FirstActionableFrame":"-","BaseDamage":"5","Angle":"65","BaseKnockBackSetKnockback":"50","LandingLag":null,"AutoCancel":null,"KnockbackGrowth":"50","MoveType":"special","IsWeightDependent":false,"Game":"Smash4","Related":{"Smash4":{"Character":"http://api.kuroganehammer.com/api/characters/name/ToonLink?game=smash4","Self":"http://api.kuroganehammer.com/api/moves/ace9b0929d5647c7a5a09a5f12646d23?game=smash4"},"Ultimate":{"Character":"http://api.kuroganehammer.com/api/characters/name/ToonLink?game=ultimate"}},"Links":[{"Rel":"self","Href":"http://api.kuroganehammer.com/api/moves/ace9b0929d5647c7a5a09a5f12646d23?game=smash4"},{"Rel":"character","Href":"http://api.kuroganehammer.com/api/characters/name/ToonLink?game=smash4"}]},{"InstanceId":"ac570b7aa9424700b96a9ca980326f06","Name":"Spin Attack (No Charge)","OwnerId":52,"Owner":"ToonLink","HitboxActive":"9-17 (Rehit rate: 4)","FirstActionableFrame":"81","BaseDamage":"1","Angle":"180/180/180/80","BaseKnockBackSetKnockback":"W: 50/50/50/10","LandingLag":null,"AutoCancel":null,"KnockbackGrowth":"100","MoveType":"special","IsWeightDependent":false,"Game":"Smash4","Related":{"Smash4":{"Character":"http://api.kuroganehammer.com/api/characters/name/ToonLink?game=smash4","Self":"http://api.kuroganehammer.com/api/moves/ac570b7aa9424700b96a9ca980326f06?game=smash4"},"Ultimate":{"Character":"http://api.kuroganehammer.com/api/characters/name/ToonLink?game=ultimate"}},"Links":[{"Rel":"self","Href":"http://api.kuroganehammer.com/api/moves/ac570b7aa9424700b96a9ca980326f06?game=smash4"},{"Rel":"character","Href":"http://api.kuroganehammer.com/api/characters/name/ToonLink?game=smash4"}]},{"InstanceId":"f75049b0604442f5958b0048abc0149e","Name":"Spin Attack (No Charge)","OwnerId":52,"Owner":"ToonLink","HitboxActive":"18-49 (Rehit rate: 5)","FirstActionableFrame":"-","BaseDamage":"1","Angle":"180/180/180/80","BaseKnockBackSetKnockback":"W: 40/40/30/10","LandingLag":null,"AutoCancel":null,"KnockbackGrowth":"100","MoveType":"special","IsWeightDependent":false,"Game":"Smash4","Related":{"Smash4":{"Character":"http://api.kuroganehammer.com/api/characters/name/ToonLink?game=smash4","Self":"http://api.kuroganehammer.com/api/moves/f75049b0604442f5958b0048abc0149e?game=smash4"},"Ultimate":{"Character":"http://api.kuroganehammer.com/api/characters/name/ToonLink?game=ultimate"}},"Links":[{"Rel":"self","Href":"http://api.kuroganehammer.com/api/moves/f75049b0604442f5958b0048abc0149e?game=smash4"},{"Rel":"character","Href":"http://api.kuroganehammer.com/api/characters/name/ToonLink?game=smash4"}]},{"InstanceId":"a51f6fbce94d45a6b3769402caa456da","Name":"Spin Attack (No Charge, Final Hit)","OwnerId":52,"Owner":"ToonLink","HitboxActive":"51","FirstActionableFrame":"-","BaseDamage":"3","Angle":"55","BaseKnockBackSetKnockback":"70","LandingLag":null,"AutoCancel":null,"KnockbackGrowth":"141","MoveType":"special","IsWeightDependent":false,"Game":"Smash4","Related":{"Smash4":{"Character":"http://api.kuroganehammer.com/api/characters/name/ToonLink?game=smash4","Self":"http://api.kuroganehammer.com/api/moves/a51f6fbce94d45a6b3769402caa456da?game=smash4"},"Ultimate":{"Character":"http://api.kuroganehammer.com/api/characters/name/ToonLink?game=ultimate"}},"Links":[{"Rel":"self","Href":"http://api.kuroganehammer.com/api/moves/a51f6fbce94d45a6b3769402caa456da?game=smash4"},{"Rel":"character","Href":"http://api.kuroganehammer.com/api/characters/name/ToonLink?game=smash4"}]},{"InstanceId":"0833758fa8584e378161284e419e32a8","Name":"Spin Attack (Air, Hit 1)","OwnerId":52,"Owner":"ToonLink","HitboxActive":"8-10","FirstActionableFrame":"-","BaseDamage":"4","Angle":"366","BaseKnockBackSetKnockback":"W: 90","LandingLag":null,"AutoCancel":null,"KnockbackGrowth":"100","MoveType":"special","IsWeightDependent":false,"Game":"Smash4","Related":{"Smash4":{"Character":"http://api.kuroganehammer.com/api/characters/name/ToonLink?game=smash4","Self":"http://api.kuroganehammer.com/api/moves/0833758fa8584e378161284e419e32a8?game=smash4"},"Ultimate":{"Character":"http://api.kuroganehammer.com/api/characters/name/ToonLink?game=ultimate"}},"Links":[{"Rel":"self","Href":"http://api.kuroganehammer.com/api/moves/0833758fa8584e378161284e419e32a8?game=smash4"},{"Rel":"character","Href":"http://api.kuroganehammer.com/api/characters/name/ToonLink?game=smash4"}]},{"InstanceId":"8ae75a80748e4b57a4a57f4c2df306c9","Name":"Spin Attack (Air, Hit 2)","OwnerId":52,"Owner":"ToonLink","HitboxActive":"16-18","FirstActionableFrame":"-","BaseDamage":"2","Angle":"366","BaseKnockBackSetKnockback":"W: 88","LandingLag":null,"AutoCancel":null,"KnockbackGrowth":"100","MoveType":"special","IsWeightDependent":false,"Game":"Smash4","Related":{"Smash4":{"Character":"http://api.kuroganehammer.com/api/characters/name/ToonLink?game=smash4","Self":"http://api.kuroganehammer.com/api/moves/8ae75a80748e4b57a4a57f4c2df306c9?game=smash4"},"Ultimate":{"Character":"http://api.kuroganehammer.com/api/characters/name/ToonLink?game=ultimate"}},"Links":[{"Rel":"self","Href":"http://api.kuroganehammer.com/api/moves/8ae75a80748e4b57a4a57f4c2df306c9?game=smash4"},{"Rel":"character","Href":"http://api.kuroganehammer.com/api/characters/name/ToonLink?game=smash4"}]},{"InstanceId":"3d2205cba6244e64a7d29a6b035e4e88","Name":"Spin Attack (Air, Hit 3)","OwnerId":52,"Owner":"ToonLink","HitboxActive":"22-24","FirstActionableFrame":"-","BaseDamage":"2","Angle":"366","BaseKnockBackSetKnockback":"W: 77","LandingLag":null,"AutoCancel":null,"KnockbackGrowth":"100","MoveType":"special","IsWeightDependent":false,"Game":"Smash4","Related":{"Smash4":{"Character":"http://api.kuroganehammer.com/api/characters/name/ToonLink?game=smash4","Self":"http://api.kuroganehammer.com/api/moves/3d2205cba6244e64a7d29a6b035e4e88?game=smash4"},"Ultimate":{"Character":"http://api.kuroganehammer.com/api/characters/name/ToonLink?game=ultimate"}},"Links":[{"Rel":"self","Href":"http://api.kuroganehammer.com/api/moves/3d2205cba6244e64a7d29a6b035e4e88?game=smash4"},{"Rel":"character","Href":"http://api.kuroganehammer.com/api/characters/name/ToonLink?game=smash4"}]},{"InstanceId":"768c9efaa10c4a14b6a400d75d4c6a9e","Name":"Spin Attack (Air, Hit 4)","OwnerId":52,"Owner":"ToonLink","HitboxActive":"31-33","FirstActionableFrame":"-","BaseDamage":"2","Angle":"85","BaseKnockBackSetKnockback":"W: 80","LandingLag":null,"AutoCancel":null,"KnockbackGrowth":"100","MoveType":"special","IsWeightDependent":false,"Game":"Smash4","Related":{"Smash4":{"Character":"http://api.kuroganehammer.com/api/characters/name/ToonLink?game=smash4","Self":"http://api.kuroganehammer.com/api/moves/768c9efaa10c4a14b6a400d75d4c6a9e?game=smash4"},"Ultimate":{"Character":"http://api.kuroganehammer.com/api/characters/name/ToonLink?game=ultimate"}},"Links":[{"Rel":"self","Href":"http://api.kuroganehammer.com/api/moves/768c9efaa10c4a14b6a400d75d4c6a9e?game=smash4"},{"Rel":"character","Href":"http://api.kuroganehammer.com/api/characters/name/ToonLink?game=smash4"}]},{"InstanceId":"bfb8cbb541084324a88af41b96147a2f","Name":"Spin Attack (Air, Hit 5)","OwnerId":52,"Owner":"ToonLink","HitboxActive":"44-48","FirstActionableFrame":"-","BaseDamage":"4","Angle":"45","BaseKnockBackSetKnockback":"40","LandingLag":null,"AutoCancel":null,"KnockbackGrowth":"170","MoveType":"special","IsWeightDependent":false,"Game":"Smash4","Related":{"Smash4":{"Character":"http://api.kuroganehammer.com/api/characters/name/ToonLink?game=smash4","Self":"http://api.kuroganehammer.com/api/moves/bfb8cbb541084324a88af41b96147a2f?game=smash4"},"Ultimate":{"Character":"http://api.kuroganehammer.com/api/characters/name/ToonLink?game=ultimate"}},"Links":[{"Rel":"self","Href":"http://api.kuroganehammer.com/api/moves/bfb8cbb541084324a88af41b96147a2f?game=smash4"},{"Rel":"character","Href":"http://api.kuroganehammer.com/api/characters/name/ToonLink?game=smash4"}]},{"InstanceId":"ac495c2c3f96489a91b5d35173020e3c","Name":"Bomb","OwnerId":52,"Owner":"ToonLink","HitboxActive":"Bomb Generated: Frame 17","FirstActionableFrame":"40","BaseDamage":"-","Angle":"-","BaseKnockBackSetKnockback":"-","LandingLag":null,"AutoCancel":null,"KnockbackGrowth":"-","MoveType":"special","IsWeightDependent":false,"Game":"Smash4","Related":{"Smash4":{"Character":"http://api.kuroganehammer.com/api/characters/name/ToonLink?game=smash4","Self":"http://api.kuroganehammer.com/api/moves/ac495c2c3f96489a91b5d35173020e3c?game=smash4"},"Ultimate":{"Character":"http://api.kuroganehammer.com/api/characters/name/ToonLink?game=ultimate"}},"Links":[{"Rel":"self","Href":"http://api.kuroganehammer.com/api/moves/ac495c2c3f96489a91b5d35173020e3c?game=smash4"},{"Rel":"character","Href":"http://api.kuroganehammer.com/api/characters/name/ToonLink?game=smash4"}]},{"InstanceId":"97787dca20db486f8f9c3eaecea7b153","Name":"Bomb","OwnerId":52,"Owner":"ToonLink","HitboxActive":"Explodes 299 Frames from Generation","FirstActionableFrame":"-","BaseDamage":"-","Angle":"70","BaseKnockBackSetKnockback":"40","LandingLag":null,"AutoCancel":null,"KnockbackGrowth":"80","MoveType":"special","IsWeightDependent":false,"Game":"Smash4","Related":{"Smash4":{"Character":"http://api.kuroganehammer.com/api/characters/name/ToonLink?game=smash4","Self":"http://api.kuroganehammer.com/api/moves/97787dca20db486f8f9c3eaecea7b153?game=smash4"},"Ultimate":{"Character":"http://api.kuroganehammer.com/api/characters/name/ToonLink?game=ultimate"}},"Links":[{"Rel":"self","Href":"http://api.kuroganehammer.com/api/moves/97787dca20db486f8f9c3eaecea7b153?game=smash4"},{"Rel":"character","Href":"http://api.kuroganehammer.com/api/characters/name/ToonLink?game=smash4"}]},{"InstanceId":"c35da243a2f34147959e7fd65860949c","Name":"Fthrow","OwnerId":52,"Owner":"ToonLink","HitboxActive":null,"FirstActionableFrame":null,"BaseDamage":"3, 4","Angle":"45","BaseKnockBackSetKnockback":"60","LandingLag":null,"AutoCancel":null,"KnockbackGrowth":"110","MoveType":"throw","IsWeightDependent":false,"Game":"Smash4","Related":{"Smash4":{"Character":"http://api.kuroganehammer.com/api/characters/name/ToonLink?game=smash4","Self":"http://api.kuroganehammer.com/api/moves/c35da243a2f34147959e7fd65860949c?game=smash4"},"Ultimate":{"Character":"http://api.kuroganehammer.com/api/characters/name/ToonLink?game=ultimate"}},"Links":[{"Rel":"self","Href":"http://api.kuroganehammer.com/api/moves/c35da243a2f34147959e7fd65860949c?game=smash4"},{"Rel":"character","Href":"http://api.kuroganehammer.com/api/characters/name/ToonLink?game=smash4"}]},{"InstanceId":"c8f0de5c4d0d47268928976426f54e82","Name":"Bthrow","OwnerId":52,"Owner":"ToonLink","HitboxActive":null,"FirstActionableFrame":null,"BaseDamage":"7","Angle":"130","BaseKnockBackSetKnockback":"60","LandingLag":null,"AutoCancel":null,"KnockbackGrowth":"120","MoveType":"throw","IsWeightDependent":false,"Game":"Smash4","Related":{"Smash4":{"Character":"http://api.kuroganehammer.com/api/characters/name/ToonLink?game=smash4","Self":"http://api.kuroganehammer.com/api/moves/c8f0de5c4d0d47268928976426f54e82?game=smash4"},"Ultimate":{"Character":"http://api.kuroganehammer.com/api/characters/name/ToonLink?game=ultimate"}},"Links":[{"Rel":"self","Href":"http://api.kuroganehammer.com/api/moves/c8f0de5c4d0d47268928976426f54e82?game=smash4"},{"Rel":"character","Href":"http://api.kuroganehammer.com/api/characters/name/ToonLink?game=smash4"}]},{"InstanceId":"f5ec9154701e413da3d947ba4f89077e","Name":"Uthrow","OwnerId":52,"Owner":"ToonLink","HitboxActive":null,"FirstActionableFrame":null,"BaseDamage":"5, 2","Angle":"92","BaseKnockBackSetKnockback":"25","LandingLag":null,"AutoCancel":null,"KnockbackGrowth":"220","MoveType":"throw","IsWeightDependent":false,"Game":"Smash4","Related":{"Smash4":{"Character":"http://api.kuroganehammer.com/api/characters/name/ToonLink?game=smash4","Self":"http://api.kuroganehammer.com/api/moves/f5ec9154701e413da3d947ba4f89077e?game=smash4"},"Ultimate":{"Character":"http://api.kuroganehammer.com/api/characters/name/ToonLink?game=ultimate"}},"Links":[{"Rel":"self","Href":"http://api.kuroganehammer.com/api/moves/f5ec9154701e413da3d947ba4f89077e?game=smash4"},{"Rel":"character","Href":"http://api.kuroganehammer.com/api/characters/name/ToonLink?game=smash4"}]},{"InstanceId":"0c8e53fe80a24c289ede5410c95be258","Name":"Dthrow","OwnerId":52,"Owner":"ToonLink","HitboxActive":null,"FirstActionableFrame":null,"BaseDamage":"3, 4","Angle":"110","BaseKnockBackSetKnockback":"60","LandingLag":null,"AutoCancel":null,"KnockbackGrowth":"110","MoveType":"throw","IsWeightDependent":true,"Game":"Smash4","Related":{"Smash4":{"Character":"http://api.kuroganehammer.com/api/characters/name/ToonLink?game=smash4","Self":"http://api.kuroganehammer.com/api/moves/0c8e53fe80a24c289ede5410c95be258?game=smash4"},"Ultimate":{"Character":"http://api.kuroganehammer.com/api/characters/name/ToonLink?game=ultimate"}},"Links":[{"Rel":"self","Href":"http://api.kuroganehammer.com/api/moves/0c8e53fe80a24c289ede5410c95be258?game=smash4"},{"Rel":"character","Href":"http://api.kuroganehammer.com/api/characters/name/ToonLink?game=smash4"}]}]